[
  {
    "asin": "B0GYXR8P84",
    "bsr_rank": 454,
    "bsr_category": "Sports & Outdoors",
    "bsr_sub_rank": 5,
    "bsr_sub_category": "Sports Collectible Flags",
    "reviews": 74,
    "rating": 4.9,
    "image_url": "https://m.media-amazon.com/images/I/61JP3+URuCL._AC_QL10_SX980_SY55_FMwebp_.jpg",
    "title": "49ft/15m World Cup Flags Football Bunting 2026 for Party Decorations 2026,48 Teams Flags Double Sides Fabric Bunting Banner for Restaurant Bar Club Garden Street Party World Cup 2026 Decorations",
    "price": 7.91,
    "scraped_at": "2026-06-30T14:09:01.208498"
  }
]