[
  {
    "asin": "B0GX1WZSQY",
    "name": "Chicken Craft Personalised Campervan Mug with Name - Panel Van Custom Colour Design - Camping Gift for Him and Her",
    "price": 11.99,
    "rank": 11,
    "reviews": 0,
    "score": 176,
    "sources": [
      "TikTok趋势",
      "Google趋势",
      "Temu热销",
      "Etsy趋势"
    ],
    "channel": "new_releases"
  },
  {
    "asin": "B0H498Q8HJ",
    "name": "Aluminium Travel Soap Dish with Lid Self Draining, Metal Soap Container Soap Tin Bar Holder Case Box for Camp Gym Hiking",
    "price": 7.29,
    "rank": 8,
    "reviews": 0,
    "score": 152,
    "sources": [
      "Reddit需求",
      "TikTok趋势",
      "Temu热销",
      "Etsy趋势"
    ],
    "channel": "new_releases"
  },
  {
    "asin": "B0CGCYW1S9",
    "name": "Sponsored Ad – ZERODECO Natural Fish Net Party Decorations, Cotton Fishnet with Fringe Curtain and Bubble Garlands for N",
    "price": 9.99,
    "rank": 7,
    "reviews": 50,
    "score": 145,
    "sources": [
      "📅 海盗说话日",
      "Google趋势",
      "Reddit需求",
      "TikTok趋势",
      "Temu热销",
      "Etsy趋势"
    ],
    "channel": "keyword_search"
  },
  {
    "asin": "B0CGCSVZG9",
    "name": "ZERODECO Nautical Decor, Natural Fish Net Party Decorations for Pirate Party, Wedding, Birthday Party, Beach Theme Party",
    "price": 8.32,
    "rank": 48,
    "reviews": 79,
    "score": 141,
    "sources": [
      "📅 海盗说话日",
      "Google趋势",
      "Reddit需求",
      "TikTok趋势",
      "Temu热销",
      "Etsy趋势"
    ],
    "channel": "keyword_search"
  },
  {
    "asin": "B0F7LQFHXB",
    "name": "BACH AND BOUJEE Pirate Birthday Cake Decoration Set - Pirate Ship, Treasure Chest, Captain, Anchor, Cannon & 'Happy Birt",
    "price": 10.82,
    "rank": 43,
    "reviews": 11,
    "score": 129,
    "sources": [
      "📅 海盗说话日",
      "TikTok趋势",
      "Temu热销",
      "Etsy趋势"
    ],
    "channel": "keyword_search"
  },
  {
    "asin": "B0FH61WJV8",
    "name": "2pcs Fish Net Decorations for Party, 80x40in Hawaiian Fishing Net Nautical Themed Fishnet for Pirate Ocean Mermaid Party",
    "price": 8.66,
    "rank": 23,
    "reviews": 17,
    "score": 125,
    "sources": [
      "📅 海盗说话日",
      "Reddit需求",
      "TikTok趋势",
      "Temu热销",
      "Etsy趋势"
    ],
    "channel": "keyword_search"
  },
  {
    "asin": "B0BB1KXF1J",
    "name": "WUERKIYA Pirate Treasure Map Backdrop Island Treasure Map Banner Nautical Tapestry Hanging Decoration for Treasure Hunt ",
    "price": 7.54,
    "rank": 27,
    "reviews": 29,
    "score": 111,
    "sources": [
      "📅 海盗说话日",
      "TikTok趋势",
      "Temu热销",
      "Etsy趋势"
    ],
    "channel": "keyword_search"
  },
  {
    "asin": "B0F7HSW16C",
    "name": "Bryndo Kids Pirate Costume Set Boys Pirate Captain Dress Up Kit with Hat Vest Sword Hook Eye Patch Earring Fancy Dress f",
    "price": 9.16,
    "rank": 10,
    "reviews": 17,
    "score": 110,
    "sources": [
      "📅 海盗说话日",
      "TikTok趋势",
      "Temu热销",
      "Etsy趋势"
    ],
    "channel": "keyword_search"
  },
  {
    "asin": "B0C4Y2PR2M",
    "name": "FRIUSATE 10Pcs Pirate Costume Accessories Set, Kids Adult Captain Costume, Pirate Head Scarf Eye Patches Earrings Pirate",
    "price": 6.66,
    "rank": 22,
    "reviews": 128,
    "score": 97,
    "sources": [
      "📅 海盗说话日",
      "Reddit需求",
      "TikTok趋势",
      "Temu热销",
      "Etsy趋势"
    ],
    "channel": "keyword_search"
  },
  {
    "asin": "B0D7TF728K",
    "name": "70Pc Pirate Party Tableware Set,Pirate Treasure Hunt Theme Banner with Pirate Napkins Paper Plates Cups and Pirates Game",
    "price": 9.41,
    "rank": 5,
    "reviews": 97,
    "score": 71,
    "sources": [
      "📅 海盗说话日",
      "Google趋势"
    ],
    "channel": "keyword_search"
  },
  {
    "asin": "B0FJQ7F5BR",
    "name": "Bryndo 6 Pcs Pirate Costume Accessories Set for Women Men, Pirate Fancy Dress with Hat Bandana Head Scarf Sash Eye Patch",
    "price": 12.49,
    "rank": 6,
    "reviews": 26,
    "score": 60,
    "sources": [
      "📅 海盗说话日",
      "Reddit需求"
    ],
    "channel": "keyword_search"
  },
  {
    "asin": "B0BMPLLGFV",
    "name": "BlinBlin Pirate Party Tableware Set - Serves 20 Guests with Plates, Cups & Napkins",
    "price": 6.82,
    "rank": 47,
    "reviews": 101,
    "score": 58,
    "sources": [
      "📅 海盗说话日",
      "Google趋势"
    ],
    "channel": "keyword_search"
  },
  {
    "asin": "B0F7HTSK4L",
    "name": "Bryndo 5PCS Pirate Costume Accessories for Adults – Hat Headscarf Sash Belt Eye Patch Anchor Necklace Fancy Dress for Ha",
    "price": 9.16,
    "rank": 37,
    "reviews": 42,
    "score": 11,
    "sources": [
      "📅 海盗说话日"
    ],
    "channel": "keyword_search"
  },
  {
    "asin": "B0D8T54KNY",
    "name": "DTOFOOT Pirate Costume Pirate Skirt Costume Women Pirat Open Design Skirt Dress Adults Head Scarf Hat Eye Patch Necklace",
    "price": 11.66,
    "rank": 48,
    "reviews": 152,
    "score": 5,
    "sources": [
      "📅 海盗说话日"
    ],
    "channel": "keyword_search"
  },
  {
    "asin": "B0G1MYWD2L",
    "name": "30 Pairs Collagen Eye Patches, Hyaluronic Acid Moisturizing & Hydrating Under Eye Gel Patches for Puffy Eyes & Dark Circ",
    "price": 7.59,
    "rank": 24,
    "reviews": 33,
    "score": -1,
    "sources": [
      "📅 海盗说话日"
    ],
    "channel": "keyword_search"
  },
  {
    "asin": "B0C8JC8TYN",
    "name": "Aomig 3 Pcs Pirate Trousers for Men, Men’s Medieval Viking Renaissance Pirate Costume with Pirate Blindfolds and Bandana",
    "price": 7.07,
    "rank": 41,
    "reviews": 47,
    "score": -5,
    "sources": [
      "📅 海盗说话日"
    ],
    "channel": "keyword_search"
  },
  {
    "asin": "B0DB1RC7GG",
    "name": "Beipegin Pirate Costume Adult Men Women,Pirate Bandana Captain Medieval Large Sash Pirate Eye Patch Necklace Earrings Ri",
    "price": 8.32,
    "rank": 36,
    "reviews": 66,
    "score": -6,
    "sources": [
      "📅 海盗说话日"
    ],
    "channel": "keyword_search"
  },
  {
    "asin": "B0CZ8Z6KD2",
    "name": "Eco-Fused 8-Piece Pirate Accessories - Cosplay Halloween Decorations - Costume Telescope, Compass, Eye Patch, Plastic Gu",
    "price": 7.49,
    "rank": 47,
    "reviews": 99,
    "score": 96,
    "sources": [
      "📅 海盗说话日",
      "Reddit需求",
      "TikTok趋势",
      "Temu热销",
      "Etsy趋势"
    ],
    "channel": "keyword_search"
  },
  {
    "asin": "B0C1RS27WN",
    "name": "Wonsta Caribbean Pirate Costume Girls Fancy Dress Girls Role Play Dress Up Party Pirate Themed Birthday Party Halloween ",
    "price": 6.65,
    "rank": 31,
    "reviews": 159,
    "score": 57,
    "sources": [
      "📅 海盗说话日",
      "TikTok趋势",
      "Temu热销",
      "Etsy趋势"
    ],
    "channel": "keyword_search"
  }
]